{
	"name": "PriceSheet",
	"properties": {
		"activities": [
			{
				"name": "Convert csv to Parquet",
				"type": "Copy",
				"dependsOn": [],
				"policy": {
					"timeout": "0.12:00:00",
					"retry": 0,
					"retryIntervalInSeconds": 30,
					"secureOutput": false,
					"secureInput": false
				},
				"userProperties": [],
				"typeProperties": {
					"source": {
						"type": "DelimitedTextSource",
						"storeSettings": {
							"type": "AzureBlobFSReadSettings",
							"recursive": false,
							"wildcardFolderPath": {
								"value": "@variables('path')",
								"type": "Expression"
							},
							"wildcardFileName": {
								"value": "@concat(variables('fileName'),'.csv')",
								"type": "Expression"
							},
							"enablePartitionDiscovery": false
						},
						"formatSettings": {
							"type": "DelimitedTextReadSettings"
						}
					},
					"sink": {
						"type": "ParquetSink",
						"storeSettings": {
							"type": "AzureBlobFSWriteSettings"
						},
						"formatSettings": {
							"type": "ParquetWriteSettings"
						}
					},
					"enableStaging": false,
					"translator": {
						"type": "TabularTranslator",
						"mappings": [
							{
								"source": {
									"name": "Meter ID",
									"type": "String",
									"physicalType": "String"
								},
								"sink": {
									"name": "MeterID",
									"type": "String",
									"physicalType": "UTF8"
								}
							},
							{
								"source": {
									"name": "Meter name",
									"type": "String",
									"physicalType": "String"
								},
								"sink": {
									"name": "MeterName",
									"type": "String",
									"physicalType": "UTF8"
								}
							},
							{
								"source": {
									"name": "Meter category",
									"type": "String",
									"physicalType": "String"
								},
								"sink": {
									"name": "MeterCategory",
									"type": "String",
									"physicalType": "UTF8"
								}
							},
							{
								"source": {
									"name": "Meter sub-category",
									"type": "String",
									"physicalType": "String"
								},
								"sink": {
									"name": "MeterSubCategory",
									"type": "String",
									"physicalType": "UTF8"
								}
							},
							{
								"source": {
									"name": "Meter region",
									"type": "String",
									"physicalType": "String"
								},
								"sink": {
									"name": "MeterRegion",
									"type": "String",
									"physicalType": "UTF8"
								}
							},
							{
								"source": {
									"name": "Unit",
									"type": "String",
									"physicalType": "String"
								},
								"sink": {
									"name": "Unit",
									"type": "String",
									"physicalType": "UTF8"
								}
							},
							{
								"source": {
									"name": "Unit of measure",
									"type": "String",
									"physicalType": "String"
								},
								"sink": {
									"name": "UnitOfMeasure",
									"type": "String",
									"physicalType": "UTF8"
								}
							},
							{
								"source": {
									"name": "Part number",
									"type": "String",
									"physicalType": "String"
								},
								"sink": {
									"name": "PartNumber",
									"type": "String",
									"physicalType": "UTF8"
								}
							},
							{
								"source": {
									"name": "Unit price",
									"type": "Double",
									"physicalType": "String"
								},
								"sink": {
									"name": "UnitPrice",
									"type": "String",
									"physicalType": "UTF8"
								}
							},
							{
								"source": {
									"name": "Currency code",
									"type": "String",
									"physicalType": "String"
								},
								"sink": {
									"name": "CurrencyCode",
									"type": "String",
									"physicalType": "UTF8"
								}
							},
							{
								"source": {
									"name": "Included quantity",
									"type": "Double",
									"physicalType": "String"
								},
								"sink": {
									"name": "IncludedQuantity",
									"type": "String",
									"physicalType": "UTF8"
								}
							},
							{
								"source": {
									"name": "Offer Id",
									"type": "String",
									"physicalType": "String"
								},
								"sink": {
									"name": "OfferId",
									"type": "String",
									"physicalType": "UTF8"
								}
							},
							{
								"source": {
									"name": "Term",
									"type": "String",
									"physicalType": "String"
								},
								"sink": {
									"name": "Term",
									"type": "String",
									"physicalType": "UTF8"
								}
							},
							{
								"source": {
									"name": "Price type",
									"type": "String",
									"physicalType": "String"
								},
								"sink": {
									"name": "PriceType",
									"type": "String",
									"physicalType": "UTF8"
								}
							}
						],
						"typeConversion": true,
						"typeConversionSettings": {
							"allowDataTruncation": true,
							"treatBooleanAsNumber": false
						}
					}
				},
				"inputs": [
					{
						"referenceName": "Adhoc_CSV_Source",
						"type": "DatasetReference"
					}
				],
				"outputs": [
					{
						"referenceName": "Parquet_File",
						"type": "DatasetReference",
						"parameters": {
							"fileName": {
								"value": "@variables('fileName')",
								"type": "Expression"
							},
							"path": {
								"value": "@variables('path')",
								"type": "Expression"
							}
						}
					}
				]
			}
		],
		"variables": {
			"path": {
				"type": "String",
				"defaultValue": "pricesheet/New"
			},
			"fileName": {
				"type": "String",
				"defaultValue": "ArmPriceSheet_Enrollment_LATEST"
			}
		},
		"folder": {
			"name": "PipelinesNotInUse/Delete"
		},
		"annotations": [],
		"lastPublishTime": "2023-08-18T10:06:08Z"
	},
	"type": "Microsoft.Synapse/workspaces/pipelines"
}